{"products":[{"id":"1","name":"pijama-de-ballena-","title":"Pijama De Ballena™","description":"Pijamas Whalas la mejor pijama de ballena que todo el mundo adora","fullDescription":"","price":"42.98","oldPrice":"85.96","quantity":1,"currency":"USD","sku":"","outOfStock":false,"isFeatured":true,"categories":[],"images":[{"url":"https://assets.nicepagecdn.com/4e587f6e/6265034/images/Diseosinttulo1.png"},{"url":"https://assets.nicepagecdn.com/4e587f6e/6265034/images/Diseosinttulo2.png"},{"url":"https://assets.nicepagecdn.com/4e587f6e/6265034/images/Diseosinttulo3.png"}],"created":1716487375623,"updated":1716504049587,"isDefault":false}],"categories":[]}